chuk_mcp_time_server/__init__.py
chuk_mcp_time_server/main.py
chuk_mcp_time_server/models.py
chuk_mcp_time_server/tools.py
chuk_mcp_time_server-0.1.11.dist-info/licenses/LICENSE.md
chuk_mcp_time_server-0.1.11.dist-info/METADATA
chuk_mcp_time_server-0.1.11.dist-info/WHEEL
chuk_mcp_time_server-0.1.11.dist-info/entry_points.txt
chuk_mcp_time_server-0.1.11.dist-info/top_level.txt
chuk_mcp_time_server-0.1.11.dist-info/RECORD
