Metadata-Version: 2.4
Name: chuk-mcp-time-server
Version: 0.1.11
Summary: MCP Time Server
Requires-Python: >=3.11
License-File: LICENSE.md
Requires-Dist: chuk-mcp-runtime>=0.1.13
Requires-Dist: mcp>=1.6.0
Requires-Dist: pydantic>=2.11.2
Requires-Dist: pyyaml>=6.0.2
Requires-Dist: pyz>=0.4.3
Dynamic: license-file
